[{"annot_id": "val-17664", "ind": 17664, "movie": "Pitch Perfect 2 (2015)", "img_fn": "movieclips_Pitch_Perfect_2/5EFY3vpKDII@44.jpg", "question_number": 0}, {"annot_id": "val-17665", "ind": 17665, "movie": "Scooby Doo 2: Monsters Unleashed (2004)", "img_fn": "movieclips_Scooby_Doo_2_Monsters_Unleashed/kHk2-mOOYQg@2.jpg", "question_number": 0}, {"annot_id": "val-17666", "ind": 17666, "movie": "Scooby Doo 2: Monsters Unleashed (2004)", "img_fn": "movieclips_Scooby_Doo_2_Monsters_Unleashed/kHk2-mOOYQg@2.jpg", "question_number": 1}, {"annot_id": "val-17667", "ind": 17667, "movie": "Scooby Doo 2: Monsters Unleashed (2004)", "img_fn": "movieclips_Scooby_Doo_2_Monsters_Unleashed/kHk2-mOOYQg@2.jpg", "question_number": 2}, {"annot_id": "val-17668", "ind": 17668, "movie": "I Saw the Devil (2010)", "img_fn": "movieclips_I_Saw_the_Devil/bK3dyRu67A8@16.jpg", "question_number": 0}, {"annot_id": "val-17669", "ind": 17669, "movie": "I Saw the Devil (2010)", "img_fn": "movieclips_I_Saw_the_Devil/bK3dyRu67A8@16.jpg", "question_number": 1}, {"annot_id": "val-17670", "ind": 17670, "movie": "I Saw the Devil (2010)", "img_fn": "movieclips_I_Saw_the_Devil/bK3dyRu67A8@16.jpg", "question_number": 2}, {"annot_id": "val-17671", "ind": 17671, "movie": "The Conjuring 2 (2016)", "img_fn": "movieclips_The_Conjuring_2/W8EhiYDVPEU@4.jpg", "question_number": 0}, {"annot_id": "val-17672", "ind": 17672, "movie": "The Conjuring 2 (2016)", "img_fn": "movieclips_The_Conjuring_2/W8EhiYDVPEU@4.jpg", "question_number": 1}, {"annot_id": "val-17673", "ind": 17673, "movie": "The Conjuring 2 (2016)", "img_fn": "movieclips_The_Conjuring_2/W8EhiYDVPEU@4.jpg", "question_number": 2}, {"annot_id": "val-17674", "ind": 17674, "movie": "Mad Hot Ballroom (2005)", "img_fn": "movieclips_Mad_Hot_Ballroom/C-DCupYm66Q@50.jpg", "question_number": 0}, {"annot_id": "val-17675", "ind": 17675, "movie": "Mad Hot Ballroom (2005)", "img_fn": "movieclips_Mad_Hot_Ballroom/C-DCupYm66Q@50.jpg", "question_number": 1}, {"annot_id": "val-17676", "ind": 17676, "movie": "The Gate (1987)", "img_fn": "movieclips_The_Gate/EmeHbU_s7Cg@4.jpg", "question_number": 0}, {"annot_id": "val-17677", "ind": 17677, "movie": "The Truman Show (1998)", "img_fn": "movieclips_The_Truman_Show/ZUKCW08_8Og@14.jpg", "question_number": 0}, {"annot_id": "val-17678", "ind": 17678, "movie": "Little Voice (1998)", "img_fn": "movieclips_Little_Voice/oBtG0gj6MxA@33.jpg", "question_number": 0}, {"annot_id": "val-17679", "ind": 17679, "movie": "Jesus' Son (1999)", "img_fn": "movieclips_Jesus_Son/ZMHEIVKg_iQ@0.jpg", "question_number": 0}, {"annot_id": "val-17680", "ind": 17680, "movie": "Jesus' Son (1999)", "img_fn": "movieclips_Jesus_Son/ZMHEIVKg_iQ@0.jpg", "question_number": 1}, {"annot_id": "val-17681", "ind": 17681, "movie": "Jesus' Son (1999)", "img_fn": "movieclips_Jesus_Son/ZMHEIVKg_iQ@0.jpg", "question_number": 2}, {"annot_id": "val-17682", "ind": 17682, "movie": "Cloak & Dagger (1984)", "img_fn": "movieclips_Cloak__Dagger/tB6Uj2RGhPU@8.jpg", "question_number": 0}, {"annot_id": "val-17683", "ind": 17683, "movie": "Cloak & Dagger (1984)", "img_fn": "movieclips_Cloak__Dagger/tB6Uj2RGhPU@8.jpg", "question_number": 1}, {"annot_id": "val-17684", "ind": 17684, "movie": "Cloak & Dagger (1984)", "img_fn": "movieclips_Cloak__Dagger/tB6Uj2RGhPU@8.jpg", "question_number": 2}, {"annot_id": "val-17685", "ind": 17685, "movie": "Talladega Nights (2006)", "img_fn": "movieclips_Talladega_Nights/i1Nh_3JCFj8@22.jpg", "question_number": 0}, {"annot_id": "val-17686", "ind": 17686, "movie": "Talladega Nights (2006)", "img_fn": "movieclips_Talladega_Nights/i1Nh_3JCFj8@22.jpg", "question_number": 1}, {"annot_id": "val-17687", "ind": 17687, "movie": "What We Do in the Shadows (2015)", "img_fn": "movieclips_What_We_Do_in_the_Shadows/e1BdvP4zenI@29.jpg", "question_number": 0}, {"annot_id": "val-17688", "ind": 17688, "movie": "What We Do in the Shadows (2015)", "img_fn": "movieclips_What_We_Do_in_the_Shadows/e1BdvP4zenI@29.jpg", "question_number": 1}, {"annot_id": "val-17689", "ind": 17689, "movie": "What We Do in the Shadows (2015)", "img_fn": "movieclips_What_We_Do_in_the_Shadows/e1BdvP4zenI@29.jpg", "question_number": 2}, {"annot_id": "val-17690", "ind": 17690, "movie": "The Wings of the Dove (1997)", "img_fn": "movieclips_The_Wings_of_the_Dove/_OzammfDblc@1.jpg", "question_number": 0}, {"annot_id": "val-17691", "ind": 17691, "movie": "The Wings of the Dove (1997)", "img_fn": "movieclips_The_Wings_of_the_Dove/_OzammfDblc@1.jpg", "question_number": 1}, {"annot_id": "val-17692", "ind": 17692, "movie": "The Wings of the Dove (1997)", "img_fn": "movieclips_The_Wings_of_the_Dove/_OzammfDblc@1.jpg", "question_number": 2}, {"annot_id": "val-17693", "ind": 17693, "movie": "Eagle vs Shark (2007)", "img_fn": "movieclips_Eagle_vs_Shark/0WjELXl_6zA@23.jpg", "question_number": 0}, {"annot_id": "val-17694", "ind": 17694, "movie": "Eagle vs Shark (2007)", "img_fn": "movieclips_Eagle_vs_Shark/0WjELXl_6zA@23.jpg", "question_number": 1}, {"annot_id": "val-17695", "ind": 17695, "movie": "Eagle vs Shark (2007)", "img_fn": "movieclips_Eagle_vs_Shark/0WjELXl_6zA@23.jpg", "question_number": 2}, {"annot_id": "val-17696", "ind": 17696, "movie": "Curse of the Pink Panther (1983)", "img_fn": "movieclips_Curse_of_the_Pink_Panther/vY04JLQa1MQ@13.jpg", "question_number": 0}, {"annot_id": "val-17697", "ind": 17697, "movie": "Meatballs (1979)", "img_fn": "movieclips_Meatballs/DONkgw00QSE@12.jpg", "question_number": 0}, {"annot_id": "val-17698", "ind": 17698, "movie": "Meatballs (1979)", "img_fn": "movieclips_Meatballs/DONkgw00QSE@12.jpg", "question_number": 1}, {"annot_id": "val-17699", "ind": 17699, "movie": "Meatballs (1979)", "img_fn": "movieclips_Meatballs/DONkgw00QSE@12.jpg", "question_number": 2}, {"annot_id": "val-17700", "ind": 17700, "movie": "Piranha 3D (2010)", "img_fn": "movieclips_Piranha_3D/ITN9541Gd8Y@42.jpg", "question_number": 0}, {"annot_id": "val-17701", "ind": 17701, "movie": "Piranha 3D (2010)", "img_fn": "movieclips_Piranha_3D/ITN9541Gd8Y@42.jpg", "question_number": 1}, {"annot_id": "val-17702", "ind": 17702, "movie": "Piranha 3D (2010)", "img_fn": "movieclips_Piranha_3D/ITN9541Gd8Y@42.jpg", "question_number": 2}, {"annot_id": "val-17703", "ind": 17703, "movie": "Coming to America (1988)", "img_fn": "movieclips_Coming_to_America/f2ygGoHSuPQ@1.jpg", "question_number": 0}, {"annot_id": "val-17704", "ind": 17704, "movie": "Coming to America (1988)", "img_fn": "movieclips_Coming_to_America/f2ygGoHSuPQ@1.jpg", "question_number": 1}, {"annot_id": "val-17705", "ind": 17705, "movie": "Pitch Perfect 2 (2015)", "img_fn": "movieclips_Pitch_Perfect_2/U7xQuGf5QHA@64.jpg", "question_number": 0}, {"annot_id": "val-17706", "ind": 17706, "movie": "Pitch Perfect 2 (2015)", "img_fn": "movieclips_Pitch_Perfect_2/U7xQuGf5QHA@64.jpg", "question_number": 1}, {"annot_id": "val-17707", "ind": 17707, "movie": "What to Expect When You're Expecting (2012)", "img_fn": "movieclips_What_to_Expect_When_Youre_Expecting/Jx401J_oG2I@24.jpg", "question_number": 0}, {"annot_id": "val-17708", "ind": 17708, "movie": "What to Expect When You're Expecting (2012)", "img_fn": "movieclips_What_to_Expect_When_Youre_Expecting/Jx401J_oG2I@24.jpg", "question_number": 1}, {"annot_id": "val-17709", "ind": 17709, "movie": "What to Expect When You're Expecting (2012)", "img_fn": "movieclips_What_to_Expect_When_Youre_Expecting/Jx401J_oG2I@24.jpg", "question_number": 2}, {"annot_id": "val-17710", "ind": 17710, "movie": "Dirty Dancing (1987)", "img_fn": "movieclips_Dirty_Dancing/-sYKI4A3uhc@18.jpg", "question_number": 0}, {"annot_id": "val-17711", "ind": 17711, "movie": "Dirty Dancing (1987)", "img_fn": "movieclips_Dirty_Dancing/-sYKI4A3uhc@18.jpg", "question_number": 1}, {"annot_id": "val-17712", "ind": 17712, "movie": "Dirty Dancing (1987)", "img_fn": "movieclips_Dirty_Dancing/-sYKI4A3uhc@18.jpg", "question_number": 2}, {"annot_id": "val-17713", "ind": 17713, "movie": "Bad Lieutenant (1992)", "img_fn": "movieclips_Bad_Lieutenant/JQRV5_auS_Q@10.jpg", "question_number": 0}, {"annot_id": "val-17714", "ind": 17714, "movie": "Bad Lieutenant (1992)", "img_fn": "movieclips_Bad_Lieutenant/JQRV5_auS_Q@10.jpg", "question_number": 1}, {"annot_id": "val-17715", "ind": 17715, "movie": "Bad Lieutenant (1992)", "img_fn": "movieclips_Bad_Lieutenant/JQRV5_auS_Q@10.jpg", "question_number": 2}, {"annot_id": "val-17716", "ind": 17716, "movie": "Lulu on the Bridge (1998)", "img_fn": "movieclips_Lulu_on_the_Bridge/o2K5JzEAzcs@12.jpg", "question_number": 0}, {"annot_id": "val-17717", "ind": 17717, "movie": "What to Expect When You're Expecting (2012)", "img_fn": "movieclips_What_to_Expect_When_Youre_Expecting/EPCFcnp0R3M@12.jpg", "question_number": 0}, {"annot_id": "val-17718", "ind": 17718, "movie": "Tommy Boy (1995)", "img_fn": "movieclips_Tommy_Boy/c1EyN9xTK94@3.jpg", "question_number": 0}, {"annot_id": "val-17719", "ind": 17719, "movie": "Tommy Boy (1995)", "img_fn": "movieclips_Tommy_Boy/c1EyN9xTK94@3.jpg", "question_number": 1}, {"annot_id": "val-17720", "ind": 17720, "movie": "Tommy Boy (1995)", "img_fn": "movieclips_Tommy_Boy/c1EyN9xTK94@3.jpg", "question_number": 2}, {"annot_id": "val-17721", "ind": 17721, "movie": "Glory (2017)", "img_fn": "movieclips_Glory/7SNohNGz_f0@6.jpg", "question_number": 0}, {"annot_id": "val-17722", "ind": 17722, "movie": "The Long Riders (1980)", "img_fn": "movieclips_The_Long_Riders/lQ8JIa98kAw@0.jpg", "question_number": 0}, {"annot_id": "val-17723", "ind": 17723, "movie": "The Long Riders (1980)", "img_fn": "movieclips_The_Long_Riders/lQ8JIa98kAw@0.jpg", "question_number": 1}, {"annot_id": "val-17724", "ind": 17724, "movie": "Cheaper by the Dozen 2 (2005)", "img_fn": "movieclips_Cheaper_by_the_Dozen_2/djUYiJu6K48@39.jpg", "question_number": 0}, {"annot_id": "val-17725", "ind": 17725, "movie": "Cheaper by the Dozen 2 (2005)", "img_fn": "movieclips_Cheaper_by_the_Dozen_2/djUYiJu6K48@39.jpg", "question_number": 1}, {"annot_id": "val-17726", "ind": 17726, "movie": "Cheaper by the Dozen 2 (2005)", "img_fn": "movieclips_Cheaper_by_the_Dozen_2/djUYiJu6K48@39.jpg", "question_number": 2}, {"annot_id": "val-17727", "ind": 17727, "movie": "The Secret Garden (1993)", "img_fn": "movieclips_The_Secret_Garden/ZFwI8ujpT0Y@23.jpg", "question_number": 0}, {"annot_id": "val-17728", "ind": 17728, "movie": "The Secret Garden (1993)", "img_fn": "movieclips_The_Secret_Garden/ZFwI8ujpT0Y@23.jpg", "question_number": 1}, {"annot_id": "val-17729", "ind": 17729, "movie": "The Secret Garden (1993)", "img_fn": "movieclips_The_Secret_Garden/ZFwI8ujpT0Y@23.jpg", "question_number": 2}, {"annot_id": "val-17730", "ind": 17730, "movie": "Pitch Perfect 2 (2015)", "img_fn": "movieclips_Pitch_Perfect_2/lssQ4w2V4XM@54.jpg", "question_number": 0}, {"annot_id": "val-17731", "ind": 17731, "movie": "29 Palms (2002)", "img_fn": "movieclips_29_Palms/nDTVpRRoqcw@3.jpg", "question_number": 0}, {"annot_id": "val-17732", "ind": 17732, "movie": "29 Palms (2002)", "img_fn": "movieclips_29_Palms/nDTVpRRoqcw@3.jpg", "question_number": 1}, {"annot_id": "val-17733", "ind": 17733, "movie": "Ash Wednesday (2002)", "img_fn": "movieclips_Ash_Wednesday/_5UWCkgkSzA@0.jpg", "question_number": 0}, {"annot_id": "val-17734", "ind": 17734, "movie": "Ash Wednesday (2002)", "img_fn": "movieclips_Ash_Wednesday/_5UWCkgkSzA@0.jpg", "question_number": 1}, {"annot_id": "val-17735", "ind": 17735, "movie": "I Now Pronounce You Chuck & Larry (2007)", "img_fn": "movieclips_I_Now_Pronounce_You_Chuck__Larry/K-cBT5AxRrg@40.jpg", "question_number": 0}, {"annot_id": "val-17736", "ind": 17736, "movie": "I Now Pronounce You Chuck & Larry (2007)", "img_fn": "movieclips_I_Now_Pronounce_You_Chuck__Larry/K-cBT5AxRrg@40.jpg", "question_number": 1}, {"annot_id": "val-17737", "ind": 17737, "movie": "Half Baked (1998)", "img_fn": "movieclips_Half_Baked/XLScUvabSr4@4.jpg", "question_number": 0}, {"annot_id": "val-17738", "ind": 17738, "movie": "Half Baked (1998)", "img_fn": "movieclips_Half_Baked/XLScUvabSr4@4.jpg", "question_number": 1}, {"annot_id": "val-17739", "ind": 17739, "movie": "American Gangster (2007)", "img_fn": "movieclips_American_Gangster/H38XiM2EOnQ@6.jpg", "question_number": 0}, {"annot_id": "val-17740", "ind": 17740, "movie": "American Gangster (2007)", "img_fn": "movieclips_American_Gangster/H38XiM2EOnQ@6.jpg", "question_number": 1}, {"annot_id": "val-17741", "ind": 17741, "movie": "American Gangster (2007)", "img_fn": "movieclips_American_Gangster/H38XiM2EOnQ@6.jpg", "question_number": 2}, {"annot_id": "val-17742", "ind": 17742, "movie": "What We Do in the Shadows (2015)", "img_fn": "movieclips_What_We_Do_in_the_Shadows/Yr3YqpkoN_o@21.jpg", "question_number": 0}, {"annot_id": "val-17743", "ind": 17743, "movie": "The United States of Leland (2003)", "img_fn": "movieclips_The_United_States_of_Leland/ioznxKkY_IE@3.jpg", "question_number": 0}, {"annot_id": "val-17744", "ind": 17744, "movie": "Employee of the Month (2006)", "img_fn": "movieclips_Employee_of_the_Month/0eC9f13FIJ0@15.jpg", "question_number": 0}, {"annot_id": "val-17745", "ind": 17745, "movie": "Employee of the Month (2006)", "img_fn": "movieclips_Employee_of_the_Month/0eC9f13FIJ0@15.jpg", "question_number": 1}, {"annot_id": "val-17746", "ind": 17746, "movie": "Rocky II (1979)", "img_fn": "movieclips_Rocky_II/z_hfmThW4fs@14.jpg", "question_number": 0}, {"annot_id": "val-17747", "ind": 17747, "movie": "Rocky II (1979)", "img_fn": "movieclips_Rocky_II/z_hfmThW4fs@14.jpg", "question_number": 1}, {"annot_id": "val-17748", "ind": 17748, "movie": "Rocky II (1979)", "img_fn": "movieclips_Rocky_II/z_hfmThW4fs@14.jpg", "question_number": 2}, {"annot_id": "val-17749", "ind": 17749, "movie": "Waiting... (2005)", "img_fn": "movieclips_Waiting.../QVw-cRLFWOI@5.jpg", "question_number": 0}, {"annot_id": "val-17750", "ind": 17750, "movie": "The Nutty Professor (1996)", "img_fn": "movieclips_The_Nutty_Professor/cZP4yFO6l78@14.jpg", "question_number": 0}, {"annot_id": "val-17751", "ind": 17751, "movie": "Mac and Me (1988)", "img_fn": "movieclips_Mac_and_Me/g0yYxO89lQA@9.jpg", "question_number": 0}, {"annot_id": "val-17752", "ind": 17752, "movie": "Mac and Me (1988)", "img_fn": "movieclips_Mac_and_Me/g0yYxO89lQA@9.jpg", "question_number": 1}, {"annot_id": "val-17753", "ind": 17753, "movie": "Mac and Me (1988)", "img_fn": "movieclips_Mac_and_Me/g0yYxO89lQA@9.jpg", "question_number": 2}, {"annot_id": "val-17754", "ind": 17754, "movie": "Pitch Perfect 2 (2015)", "img_fn": "movieclips_Pitch_Perfect_2/MCFqMGgv1YY@11.jpg", "question_number": 0}, {"annot_id": "val-17755", "ind": 17755, "movie": "Think Like a Man Too (2014)", "img_fn": "movieclips_Think_Like_a_Man_Too/iKS_327EF84@31.jpg", "question_number": 0}, {"annot_id": "val-17756", "ind": 17756, "movie": "Shallow Hal (2001)", "img_fn": "movieclips_Shallow_Hal/G3BQd2K3maI@29.jpg", "question_number": 0}, {"annot_id": "val-17757", "ind": 17757, "movie": "Shallow Hal (2001)", "img_fn": "movieclips_Shallow_Hal/G3BQd2K3maI@29.jpg", "question_number": 1}, {"annot_id": "val-17758", "ind": 17758, "movie": "Knowing (2009)", "img_fn": "movieclips_Knowing/EzocwDE3VK4@12.jpg", "question_number": 0}, {"annot_id": "val-17759", "ind": 17759, "movie": "Knowing (2009)", "img_fn": "movieclips_Knowing/EzocwDE3VK4@12.jpg", "question_number": 1}]