[{"annot_id": "val-20928", "ind": 20928, "movie": "Coming to America (1988)", "img_fn": "movieclips_Coming_to_America/ExG7Ut6DJ1E@5.jpg", "question_number": 2}, {"annot_id": "val-20929", "ind": 20929, "movie": "Midgets Vs. Mascots (2009)", "img_fn": "movieclips_Midgets_Vs._Mascots/-meMCDrOmpo@0.jpg", "question_number": 1}, {"annot_id": "val-20930", "ind": 20930, "movie": "Talladega Nights (2006)", "img_fn": "movieclips_Talladega_Nights/QN5dfOs4TMY@32.jpg", "question_number": 2}, {"annot_id": "val-20931", "ind": 20931, "movie": "The Secret Garden (1993)", "img_fn": "movieclips_The_Secret_Garden/ZFwI8ujpT0Y@25.jpg", "question_number": 1}, {"annot_id": "val-20932", "ind": 20932, "movie": "Cheaper by the Dozen 2 (2005)", "img_fn": "movieclips_Cheaper_by_the_Dozen_2/5e7c30eNNy4@17.jpg", "question_number": 3}, {"annot_id": "val-20933", "ind": 20933, "movie": "Cheaper by the Dozen 2 (2005)", "img_fn": "movieclips_Cheaper_by_the_Dozen_2/5e7c30eNNy4@17.jpg", "question_number": 4}, {"annot_id": "val-20934", "ind": 20934, "movie": "Mad Hot Ballroom (2005)", "img_fn": "movieclips_Mad_Hot_Ballroom/9oDHw4wwTQI@13.jpg", "question_number": 2}, {"annot_id": "val-20935", "ind": 20935, "movie": "Mad Hot Ballroom (2005)", "img_fn": "movieclips_Mad_Hot_Ballroom/9oDHw4wwTQI@13.jpg", "question_number": 3}, {"annot_id": "val-20936", "ind": 20936, "movie": "Mad Hot Ballroom (2005)", "img_fn": "movieclips_Mad_Hot_Ballroom/9oDHw4wwTQI@13.jpg", "question_number": 4}, {"annot_id": "val-20937", "ind": 20937, "movie": "Talladega Nights (2006)", "img_fn": "movieclips_Talladega_Nights/i1Nh_3JCFj8@13.jpg", "question_number": 3}, {"annot_id": "val-20938", "ind": 20938, "movie": "Talladega Nights (2006)", "img_fn": "movieclips_Talladega_Nights/i1Nh_3JCFj8@13.jpg", "question_number": 4}, {"annot_id": "val-20939", "ind": 20939, "movie": "Talladega Nights (2006)", "img_fn": "movieclips_Talladega_Nights/i1Nh_3JCFj8@13.jpg", "question_number": 5}, {"annot_id": "val-20940", "ind": 20940, "movie": "Basquiat (1996)", "img_fn": "movieclips_Basquiat/Z-5JqDEHfe8@16.jpg", "question_number": 2}, {"annot_id": "val-20941", "ind": 20941, "movie": "Basquiat (1996)", "img_fn": "movieclips_Basquiat/Z-5JqDEHfe8@16.jpg", "question_number": 3}, {"annot_id": "val-20942", "ind": 20942, "movie": "Basquiat (1996)", "img_fn": "movieclips_Basquiat/Z-5JqDEHfe8@16.jpg", "question_number": 4}, {"annot_id": "val-20943", "ind": 20943, "movie": "Beyond the Valley of the Dolls (1970)", "img_fn": "movieclips_Beyond_the_Valley_of_the_Dolls/Y10g9umKQcM@21.jpg", "question_number": 0}, {"annot_id": "val-20944", "ind": 20944, "movie": "Billy Elliot (2000)", "img_fn": "movieclips_Billy_Elliot/8TOTUOFMjuo@1.jpg", "question_number": 2}, {"annot_id": "val-20945", "ind": 20945, "movie": "Billy Elliot (2000)", "img_fn": "movieclips_Billy_Elliot/8TOTUOFMjuo@1.jpg", "question_number": 3}, {"annot_id": "val-20946", "ind": 20946, "movie": "Billy Elliot (2000)", "img_fn": "movieclips_Billy_Elliot/8TOTUOFMjuo@1.jpg", "question_number": 4}, {"annot_id": "val-20947", "ind": 20947, "movie": "Abbott and Costello Meet the Mummy (1955)", "img_fn": "movieclips_Abbott_and_Costello_Meet_the_Mummy/Yg6sZ2htZfc@4.jpg", "question_number": 1}, {"annot_id": "val-20948", "ind": 20948, "movie": "Stateside (2004)", "img_fn": "movieclips_Stateside/qgE9Lbwyzc0@32.jpg", "question_number": 3}, {"annot_id": "val-20949", "ind": 20949, "movie": "Stateside (2004)", "img_fn": "movieclips_Stateside/qgE9Lbwyzc0@32.jpg", "question_number": 4}, {"annot_id": "val-20950", "ind": 20950, "movie": "Stateside (2004)", "img_fn": "movieclips_Stateside/qgE9Lbwyzc0@32.jpg", "question_number": 5}, {"annot_id": "val-20951", "ind": 20951, "movie": "Dirty Dancing (1987)", "img_fn": "movieclips_Dirty_Dancing/WRdy4CcRchU@14.jpg", "question_number": 1}, {"annot_id": "val-20952", "ind": 20952, "movie": "Dirty Dancing (1987)", "img_fn": "movieclips_Dirty_Dancing/WRdy4CcRchU@14.jpg", "question_number": 2}, {"annot_id": "val-20953", "ind": 20953, "movie": "Dirty Dancing (1987)", "img_fn": "movieclips_Dirty_Dancing/WRdy4CcRchU@14.jpg", "question_number": 3}, {"annot_id": "val-20954", "ind": 20954, "movie": "Midgets Vs. Mascots (2009)", "img_fn": "movieclips_Midgets_Vs._Mascots/51y64KtGGRI@4.jpg", "question_number": 3}, {"annot_id": "val-20955", "ind": 20955, "movie": "Midgets Vs. Mascots (2009)", "img_fn": "movieclips_Midgets_Vs._Mascots/51y64KtGGRI@4.jpg", "question_number": 4}, {"annot_id": "val-20956", "ind": 20956, "movie": "Midgets Vs. Mascots (2009)", "img_fn": "movieclips_Midgets_Vs._Mascots/51y64KtGGRI@4.jpg", "question_number": 5}, {"annot_id": "val-20957", "ind": 20957, "movie": "Just Married (2003)", "img_fn": "movieclips_Just_Married/TKBQuK1988w@10.jpg", "question_number": 3}, {"annot_id": "val-20958", "ind": 20958, "movie": "Lottery Ticket(2010)", "img_fn": "movieclips_Lottery_Ticket/lhHv2EyaaNc@2.jpg", "question_number": 1}, {"annot_id": "val-20959", "ind": 20959, "movie": "Piranha 3D (2010)", "img_fn": "movieclips_Piranha_3D/ifDBVFHT1DU@7.jpg", "question_number": 3}, {"annot_id": "val-20960", "ind": 20960, "movie": "Reno 911!: Miami (2007)", "img_fn": "movieclips_Reno_911_Miami/H53kBYo1Jx8@26.jpg", "question_number": 3}, {"annot_id": "val-20961", "ind": 20961, "movie": "Rocky II (1979)", "img_fn": "movieclips_Rocky_II/4uRK1MPvUps@69.jpg", "question_number": 3}, {"annot_id": "val-20962", "ind": 20962, "movie": "Rocky II (1979)", "img_fn": "movieclips_Rocky_II/4uRK1MPvUps@69.jpg", "question_number": 4}, {"annot_id": "val-20963", "ind": 20963, "movie": "Rocky II (1979)", "img_fn": "movieclips_Rocky_II/4uRK1MPvUps@69.jpg", "question_number": 5}, {"annot_id": "val-20964", "ind": 20964, "movie": "Coming to America (1988)", "img_fn": "movieclips_Coming_to_America/ExG7Ut6DJ1E@11.jpg", "question_number": 1}, {"annot_id": "val-20965", "ind": 20965, "movie": "Dreamgirls (2006)", "img_fn": "movieclips_Dreamgirls/53o7_NqrTQA@56.jpg", "question_number": 2}, {"annot_id": "val-20966", "ind": 20966, "movie": "Extract (2009)", "img_fn": "movieclips_Extract/Vwd5W0M3ZC4@1.jpg", "question_number": 1}, {"annot_id": "val-20967", "ind": 20967, "movie": "Extract (2009)", "img_fn": "movieclips_Extract/Vwd5W0M3ZC4@1.jpg", "question_number": 2}, {"annot_id": "val-20968", "ind": 20968, "movie": "Extract (2009)", "img_fn": "movieclips_Extract/Vwd5W0M3ZC4@1.jpg", "question_number": 3}, {"annot_id": "val-20969", "ind": 20969, "movie": "Inglourious Basterds (2009)", "img_fn": "movieclips_Inglourious_Basterds/7LFtoz9sERo@4.jpg", "question_number": 3}, {"annot_id": "val-20970", "ind": 20970, "movie": "True Grit (1969)", "img_fn": "movieclips_True_Grit/6DU0mdThjg4@0.jpg", "question_number": 1}, {"annot_id": "val-20971", "ind": 20971, "movie": "True Grit (1969)", "img_fn": "movieclips_True_Grit/6DU0mdThjg4@0.jpg", "question_number": 2}, {"annot_id": "val-20972", "ind": 20972, "movie": "True Grit (1969)", "img_fn": "movieclips_True_Grit/6DU0mdThjg4@0.jpg", "question_number": 3}, {"annot_id": "val-20973", "ind": 20973, "movie": "The Imperialists Are Still Alive!(2010)", "img_fn": "movieclips_The_Imperialists_Are_Still_Alive/s4heu0mPm-I@0.jpg", "question_number": 3}, {"annot_id": "val-20974", "ind": 20974, "movie": "Beyond Borders (2003)", "img_fn": "movieclips_Beyond_Borders/8RRzvri051s@8.jpg", "question_number": 1}, {"annot_id": "val-20975", "ind": 20975, "movie": "Beyond Borders (2003)", "img_fn": "movieclips_Beyond_Borders/8RRzvri051s@8.jpg", "question_number": 2}, {"annot_id": "val-20976", "ind": 20976, "movie": "Beyond Borders (2003)", "img_fn": "movieclips_Beyond_Borders/8RRzvri051s@8.jpg", "question_number": 3}, {"annot_id": "val-20977", "ind": 20977, "movie": "The Dangerous Lives of Altar Boys (2002)", "img_fn": "movieclips_The_Dangerous_Lives_of_Altar_Boys/u3xawRs6Rik@16.jpg", "question_number": 2}, {"annot_id": "val-20978", "ind": 20978, "movie": "The Dangerous Lives of Altar Boys (2002)", "img_fn": "movieclips_The_Dangerous_Lives_of_Altar_Boys/u3xawRs6Rik@16.jpg", "question_number": 3}, {"annot_id": "val-20979", "ind": 20979, "movie": "The Dangerous Lives of Altar Boys (2002)", "img_fn": "movieclips_The_Dangerous_Lives_of_Altar_Boys/u3xawRs6Rik@16.jpg", "question_number": 4}, {"annot_id": "val-20980", "ind": 20980, "movie": "Employee of the Month (2006)", "img_fn": "movieclips_Employee_of_the_Month/dKFZ4T_Y9Pw@2.jpg", "question_number": 3}, {"annot_id": "val-20981", "ind": 20981, "movie": "Basquiat (1996)", "img_fn": "movieclips_Basquiat/qM8jk56Vj9Y@30.jpg", "question_number": 3}, {"annot_id": "val-20982", "ind": 20982, "movie": "Basquiat (1996)", "img_fn": "movieclips_Basquiat/qM8jk56Vj9Y@30.jpg", "question_number": 4}, {"annot_id": "val-20983", "ind": 20983, "movie": "It's Alive (2008)", "img_fn": "movieclips_Its_Alive/zqIOu4ki5-Q@7.jpg", "question_number": 3}, {"annot_id": "val-20984", "ind": 20984, "movie": "It's Alive (2008)", "img_fn": "movieclips_Its_Alive/zqIOu4ki5-Q@7.jpg", "question_number": 4}, {"annot_id": "val-20985", "ind": 20985, "movie": "It's Alive (2008)", "img_fn": "movieclips_Its_Alive/zqIOu4ki5-Q@7.jpg", "question_number": 5}, {"annot_id": "val-20986", "ind": 20986, "movie": "Heat (1986)", "img_fn": "movieclips_Heat/zMbx4rZOMig@6.jpg", "question_number": 3}, {"annot_id": "val-20987", "ind": 20987, "movie": "Shallow Hal (2001)", "img_fn": "movieclips_Shallow_Hal/K4j25DUQLgE@49.jpg", "question_number": 1}, {"annot_id": "val-20988", "ind": 20988, "movie": "Glory (2017)", "img_fn": "movieclips_Glory/7SNohNGz_f0@50.jpg", "question_number": 3}, {"annot_id": "val-20989", "ind": 20989, "movie": "Glory (2017)", "img_fn": "movieclips_Glory/7SNohNGz_f0@50.jpg", "question_number": 4}, {"annot_id": "val-20990", "ind": 20990, "movie": "Glory (2017)", "img_fn": "movieclips_Glory/7SNohNGz_f0@50.jpg", "question_number": 5}, {"annot_id": "val-20991", "ind": 20991, "movie": "Employee of the Month (2006)", "img_fn": "movieclips_Employee_of_the_Month/P63QUmBOP08@12.jpg", "question_number": 2}, {"annot_id": "val-20992", "ind": 20992, "movie": "Employee of the Month (2006)", "img_fn": "movieclips_Employee_of_the_Month/P63QUmBOP08@12.jpg", "question_number": 3}, {"annot_id": "val-20993", "ind": 20993, "movie": "Dune (1984)", "img_fn": "movieclips_Dune/aoPKajvq3gE@39.jpg", "question_number": 1}, {"annot_id": "val-20994", "ind": 20994, "movie": "Futureworld (1976)", "img_fn": "movieclips_Futureworld/ywJW8-m8Lq8@14.jpg", "question_number": 1}, {"annot_id": "val-20995", "ind": 20995, "movie": "Futureworld (1976)", "img_fn": "movieclips_Futureworld/ywJW8-m8Lq8@14.jpg", "question_number": 2}, {"annot_id": "val-20996", "ind": 20996, "movie": "The Substitute (1996)", "img_fn": "movieclips_The_Substitute/JMpTeDvOnLA@13.jpg", "question_number": 1}, {"annot_id": "val-20997", "ind": 20997, "movie": "Curse of the Pink Panther (1983)", "img_fn": "movieclips_Curse_of_the_Pink_Panther/P4PPhm_fJug@2.jpg", "question_number": 3}, {"annot_id": "val-20998", "ind": 20998, "movie": "Curse of the Pink Panther (1983)", "img_fn": "movieclips_Curse_of_the_Pink_Panther/P4PPhm_fJug@2.jpg", "question_number": 4}, {"annot_id": "val-20999", "ind": 20999, "movie": "Curse of the Pink Panther (1983)", "img_fn": "movieclips_Curse_of_the_Pink_Panther/P4PPhm_fJug@2.jpg", "question_number": 5}, {"annot_id": "val-21000", "ind": 21000, "movie": "Piranha 3D (2010)", "img_fn": "movieclips_Piranha_3D/71GRwoL1tdA@14.jpg", "question_number": 1}, {"annot_id": "val-21001", "ind": 21001, "movie": "The Lincoln Lawyer (2011)", "img_fn": "movieclips_The_Lincoln_Lawyer/mPoxI4PmAl8@0.jpg", "question_number": 1}, {"annot_id": "val-21002", "ind": 21002, "movie": "Last Tango in Paris (1972)", "img_fn": "movieclips_Last_Tango_in_Paris/dQGlAzHgPw8@26.jpg", "question_number": 2}, {"annot_id": "val-21003", "ind": 21003, "movie": "Last Tango in Paris (1972)", "img_fn": "movieclips_Last_Tango_in_Paris/dQGlAzHgPw8@26.jpg", "question_number": 3}, {"annot_id": "val-21004", "ind": 21004, "movie": "Tales from the Darkside (1990)", "img_fn": "movieclips_Tales_from_the_Darkside/-SJAzpHg4s8@17.jpg", "question_number": 1}, {"annot_id": "val-21005", "ind": 21005, "movie": "Scrooged (1988)", "img_fn": "movieclips_Scrooged/3kX6rf9uw7w@6.jpg", "question_number": 2}, {"annot_id": "val-21006", "ind": 21006, "movie": "Scrooged (1988)", "img_fn": "movieclips_Scrooged/3kX6rf9uw7w@6.jpg", "question_number": 3}, {"annot_id": "val-21007", "ind": 21007, "movie": "Scrooged (1988)", "img_fn": "movieclips_Scrooged/3kX6rf9uw7w@6.jpg", "question_number": 4}, {"annot_id": "val-21008", "ind": 21008, "movie": "The Nutty Professor (1996)", "img_fn": "movieclips_The_Nutty_Professor/BS8zi7Dg8TM@11.jpg", "question_number": 3}, {"annot_id": "val-21009", "ind": 21009, "movie": "The Frighteners (1996)", "img_fn": "movieclips_The_Frighteners/alh8b1lYuRU@29.jpg", "question_number": 1}, {"annot_id": "val-21010", "ind": 21010, "movie": "The Frighteners (1996)", "img_fn": "movieclips_The_Frighteners/alh8b1lYuRU@29.jpg", "question_number": 2}, {"annot_id": "val-21011", "ind": 21011, "movie": "Futureworld (1976)", "img_fn": "movieclips_Futureworld/dDU99ZOBhcU@2.jpg", "question_number": 1}, {"annot_id": "val-21012", "ind": 21012, "movie": "Futureworld (1976)", "img_fn": "movieclips_Futureworld/dDU99ZOBhcU@2.jpg", "question_number": 2}, {"annot_id": "val-21013", "ind": 21013, "movie": "Futureworld (1976)", "img_fn": "movieclips_Futureworld/dDU99ZOBhcU@2.jpg", "question_number": 3}, {"annot_id": "val-21014", "ind": 21014, "movie": "Employee of the Month (2006)", "img_fn": "movieclips_Employee_of_the_Month/EKd7hAoXDPU@8.jpg", "question_number": 2}, {"annot_id": "val-21015", "ind": 21015, "movie": "Employee of the Month (2006)", "img_fn": "movieclips_Employee_of_the_Month/EKd7hAoXDPU@8.jpg", "question_number": 3}, {"annot_id": "val-21016", "ind": 21016, "movie": "Employee of the Month (2006)", "img_fn": "movieclips_Employee_of_the_Month/EKd7hAoXDPU@8.jpg", "question_number": 4}, {"annot_id": "val-21017", "ind": 21017, "movie": "Basquiat (1996)", "img_fn": "movieclips_Basquiat/qM8jk56Vj9Y@8.jpg", "question_number": 3}, {"annot_id": "val-21018", "ind": 21018, "movie": "Rough Night (2017)", "img_fn": "movieclips_Rough_Night/ra9UQb-OVqQ@10.jpg", "question_number": 1}, {"annot_id": "val-21019", "ind": 21019, "movie": "Rough Night (2017)", "img_fn": "movieclips_Rough_Night/ra9UQb-OVqQ@10.jpg", "question_number": 2}, {"annot_id": "val-21020", "ind": 21020, "movie": "Rough Night (2017)", "img_fn": "movieclips_Rough_Night/ra9UQb-OVqQ@10.jpg", "question_number": 3}, {"annot_id": "val-21021", "ind": 21021, "movie": "Mad Hot Ballroom (2005)", "img_fn": "movieclips_Mad_Hot_Ballroom/1RTpXJVozSY@10.jpg", "question_number": 1}, {"annot_id": "val-21022", "ind": 21022, "movie": "Mad Hot Ballroom (2005)", "img_fn": "movieclips_Mad_Hot_Ballroom/1RTpXJVozSY@10.jpg", "question_number": 2}, {"annot_id": "val-21023", "ind": 21023, "movie": "Mad Hot Ballroom (2005)", "img_fn": "movieclips_Mad_Hot_Ballroom/1RTpXJVozSY@10.jpg", "question_number": 3}]