[{"annot_id": "val-23040", "ind": 23040, "movie": "Fat Man and Little Boy (1989)", "img_fn": "movieclips_Fat_Man_and_Little_Boy/2djG7snKS8w@11.jpg", "question_number": 1}, {"annot_id": "val-23041", "ind": 23041, "movie": "Fat Man and Little Boy (1989)", "img_fn": "movieclips_Fat_Man_and_Little_Boy/2djG7snKS8w@11.jpg", "question_number": 2}, {"annot_id": "val-23042", "ind": 23042, "movie": "Fat Man and Little Boy (1989)", "img_fn": "movieclips_Fat_Man_and_Little_Boy/2djG7snKS8w@11.jpg", "question_number": 3}, {"annot_id": "val-23043", "ind": 23043, "movie": "How to Stuff a Wild Bikini (1965)", "img_fn": "movieclips_How_to_Stuff_a_Wild_Bikini/61_aprVh2FQ@2.jpg", "question_number": 1}, {"annot_id": "val-23044", "ind": 23044, "movie": "How to Stuff a Wild Bikini (1965)", "img_fn": "movieclips_How_to_Stuff_a_Wild_Bikini/61_aprVh2FQ@2.jpg", "question_number": 2}, {"annot_id": "val-23045", "ind": 23045, "movie": "How to Stuff a Wild Bikini (1965)", "img_fn": "movieclips_How_to_Stuff_a_Wild_Bikini/61_aprVh2FQ@2.jpg", "question_number": 3}, {"annot_id": "val-23046", "ind": 23046, "movie": "Scrooged (1988)", "img_fn": "movieclips_Scrooged/mvmAa1cYZK4@12.jpg", "question_number": 1}, {"annot_id": "val-23047", "ind": 23047, "movie": "Scrooged (1988)", "img_fn": "movieclips_Scrooged/mvmAa1cYZK4@12.jpg", "question_number": 2}, {"annot_id": "val-23048", "ind": 23048, "movie": "Scrooged (1988)", "img_fn": "movieclips_Scrooged/mvmAa1cYZK4@12.jpg", "question_number": 3}, {"annot_id": "val-23049", "ind": 23049, "movie": "What We Do in the Shadows (2015)", "img_fn": "movieclips_What_We_Do_in_the_Shadows/Yr3YqpkoN_o@5.jpg", "question_number": 2}, {"annot_id": "val-23050", "ind": 23050, "movie": "What We Do in the Shadows (2015)", "img_fn": "movieclips_What_We_Do_in_the_Shadows/Yr3YqpkoN_o@5.jpg", "question_number": 3}, {"annot_id": "val-23051", "ind": 23051, "movie": "Finding Neverland (2004)", "img_fn": "movieclips_Finding_Neverland/E3B_XdL7Z6Y@3.jpg", "question_number": 1}, {"annot_id": "val-23052", "ind": 23052, "movie": "Finding Neverland (2004)", "img_fn": "movieclips_Finding_Neverland/E3B_XdL7Z6Y@3.jpg", "question_number": 2}, {"annot_id": "val-23053", "ind": 23053, "movie": "Finding Neverland (2004)", "img_fn": "movieclips_Finding_Neverland/E3B_XdL7Z6Y@3.jpg", "question_number": 3}, {"annot_id": "val-23054", "ind": 23054, "movie": "Happy Death Day (2017)", "img_fn": "movieclips_Happy_Death_Day/YAmnMBHMPso@5.jpg", "question_number": 1}, {"annot_id": "val-23055", "ind": 23055, "movie": "Pitch Perfect 2 (2015)", "img_fn": "movieclips_Pitch_Perfect_2/rSCm0viS2mM@16.jpg", "question_number": 1}, {"annot_id": "val-23056", "ind": 23056, "movie": "The Nutty Professor (1996)", "img_fn": "movieclips_The_Nutty_Professor/7IrB1OE9Blo@3.jpg", "question_number": 1}, {"annot_id": "val-23057", "ind": 23057, "movie": "Uncommon Valor (1983)", "img_fn": "movieclips_Uncommon_Valor/qXTTXNZucIU@35.jpg", "question_number": 2}, {"annot_id": "val-23058", "ind": 23058, "movie": "Scrooged (1988)", "img_fn": "movieclips_Scrooged/3kX6rf9uw7w@41.jpg", "question_number": 1}, {"annot_id": "val-23059", "ind": 23059, "movie": "A Smile Like Yours (1997)", "img_fn": "movieclips_A_Smile_Like_Yours/S4YcLymVzXw@5.jpg", "question_number": 3}, {"annot_id": "val-23060", "ind": 23060, "movie": "Coming to America (1988)", "img_fn": "movieclips_Coming_to_America/a_Txm9dQuhM@1.jpg", "question_number": 2}, {"annot_id": "val-23061", "ind": 23061, "movie": "Cloak & Dagger (1984)", "img_fn": "movieclips_Cloak__Dagger/Kmn7tIRUImY@5.jpg", "question_number": 1}, {"annot_id": "val-23062", "ind": 23062, "movie": "American Pie 2 (2001)", "img_fn": "movieclips_American_Pie_2/hEDeIvU1si8@25.jpg", "question_number": 2}, {"annot_id": "val-23063", "ind": 23063, "movie": "Super Troopers (2001)", "img_fn": "movieclips_Super_Troopers/0zgTcrZ5030@32.jpg", "question_number": 1}, {"annot_id": "val-23064", "ind": 23064, "movie": "Lost and Delirious (2001)", "img_fn": "movieclips_Lost_and_Delirious/hgAlSQ4Ckz0@6.jpg", "question_number": 1}, {"annot_id": "val-23065", "ind": 23065, "movie": "Lost and Delirious (2001)", "img_fn": "movieclips_Lost_and_Delirious/hgAlSQ4Ckz0@6.jpg", "question_number": 2}, {"annot_id": "val-23066", "ind": 23066, "movie": "Andre (1994)", "img_fn": "movieclips_Andre/cjS-Y6WsWMg@16.jpg", "question_number": 3}, {"annot_id": "val-23067", "ind": 23067, "movie": "American Gangster (2007)", "img_fn": "movieclips_American_Gangster/H38XiM2EOnQ@2.jpg", "question_number": 2}, {"annot_id": "val-23068", "ind": 23068, "movie": "American Gangster (2007)", "img_fn": "movieclips_American_Gangster/H38XiM2EOnQ@2.jpg", "question_number": 3}, {"annot_id": "val-23069", "ind": 23069, "movie": "American Gangster (2007)", "img_fn": "movieclips_American_Gangster/H38XiM2EOnQ@2.jpg", "question_number": 4}, {"annot_id": "val-23070", "ind": 23070, "movie": "The Man with the Golden Gun (1974)", "img_fn": "movieclips_The_Man_with_the_Golden_Gun/WCKRXHDI9Ro@45.jpg", "question_number": 3}, {"annot_id": "val-23071", "ind": 23071, "movie": "Pitch Perfect 2 (2015)", "img_fn": "movieclips_Pitch_Perfect_2/lX4H0NmDMck@74.jpg", "question_number": 2}, {"annot_id": "val-23072", "ind": 23072, "movie": "Glory (2017)", "img_fn": "movieclips_Glory/7SNohNGz_f0@52.jpg", "question_number": 1}, {"annot_id": "val-23073", "ind": 23073, "movie": "Glory (2017)", "img_fn": "movieclips_Glory/7SNohNGz_f0@52.jpg", "question_number": 2}, {"annot_id": "val-23074", "ind": 23074, "movie": "Glory (2017)", "img_fn": "movieclips_Glory/7SNohNGz_f0@52.jpg", "question_number": 3}, {"annot_id": "val-23075", "ind": 23075, "movie": "Eagle vs Shark (2007)", "img_fn": "movieclips_Eagle_vs_Shark/2GMpuN48u5c@19.jpg", "question_number": 3}, {"annot_id": "val-23076", "ind": 23076, "movie": "Coming to America (1988)", "img_fn": "movieclips_Coming_to_America/IZQFJ6hZNJc@25.jpg", "question_number": 2}, {"annot_id": "val-23077", "ind": 23077, "movie": "Coming to America (1988)", "img_fn": "movieclips_Coming_to_America/IZQFJ6hZNJc@25.jpg", "question_number": 3}, {"annot_id": "val-23078", "ind": 23078, "movie": "Coming to America (1988)", "img_fn": "movieclips_Coming_to_America/IZQFJ6hZNJc@25.jpg", "question_number": 4}, {"annot_id": "val-23079", "ind": 23079, "movie": "Waiting... (2005)", "img_fn": "movieclips_Waiting.../ckremwNAupg@0.jpg", "question_number": 1}, {"annot_id": "val-23080", "ind": 23080, "movie": "Waiting... (2005)", "img_fn": "movieclips_Waiting.../ckremwNAupg@0.jpg", "question_number": 2}, {"annot_id": "val-23081", "ind": 23081, "movie": "Waiting... (2005)", "img_fn": "movieclips_Waiting.../ckremwNAupg@0.jpg", "question_number": 3}, {"annot_id": "val-23082", "ind": 23082, "movie": "American Gigolo (1980)", "img_fn": "movieclips_American_Gigolo/dRwiGgbaM84@4.jpg", "question_number": 2}, {"annot_id": "val-23083", "ind": 23083, "movie": "American Gigolo (1980)", "img_fn": "movieclips_American_Gigolo/dRwiGgbaM84@4.jpg", "question_number": 3}, {"annot_id": "val-23084", "ind": 23084, "movie": "American Gigolo (1980)", "img_fn": "movieclips_American_Gigolo/dRwiGgbaM84@4.jpg", "question_number": 4}, {"annot_id": "val-23085", "ind": 23085, "movie": "Muriel's Wedding (1994)", "img_fn": "movieclips_Muriels_Wedding/m0uAIT2O5P0@0.jpg", "question_number": 1}, {"annot_id": "val-23086", "ind": 23086, "movie": "Bad Lieutenant (1992)", "img_fn": "movieclips_Bad_Lieutenant/cQA8oY5pwJQ@27.jpg", "question_number": 1}, {"annot_id": "val-23087", "ind": 23087, "movie": "Rough Night (2017)", "img_fn": "movieclips_Rough_Night/SwOfGb9QwTc@2.jpg", "question_number": 1}, {"annot_id": "val-23088", "ind": 23088, "movie": "Guess Who's Coming to Dinner (1967)", "img_fn": "movieclips_Guess_Whos_Coming_to_Dinner/ejUWeYTslb0@15.jpg", "question_number": 2}, {"annot_id": "val-23089", "ind": 23089, "movie": "Epoch (2001)", "img_fn": "movieclips_Epoch/cHJd_bAK9C0@20.jpg", "question_number": 1}, {"annot_id": "val-23090", "ind": 23090, "movie": "West Side Story (1961)", "img_fn": "movieclips_West_Side_Story/hMMAB3MNCKw@12.jpg", "question_number": 1}, {"annot_id": "val-23091", "ind": 23091, "movie": "West Side Story (1961)", "img_fn": "movieclips_West_Side_Story/hMMAB3MNCKw@12.jpg", "question_number": 2}, {"annot_id": "val-23092", "ind": 23092, "movie": "West Side Story (1961)", "img_fn": "movieclips_West_Side_Story/hMMAB3MNCKw@12.jpg", "question_number": 3}, {"annot_id": "val-23093", "ind": 23093, "movie": "A Mighty Wind (2003)", "img_fn": "movieclips_A_Mighty_Wind/5gN8YA_xeY8@5.jpg", "question_number": 2}, {"annot_id": "val-23094", "ind": 23094, "movie": "Reno 911!: Miami (2007)", "img_fn": "movieclips_Reno_911_Miami/9G4TzgRUKGI@17.jpg", "question_number": 3}, {"annot_id": "val-23095", "ind": 23095, "movie": "Reno 911!: Miami (2007)", "img_fn": "movieclips_Reno_911_Miami/9G4TzgRUKGI@17.jpg", "question_number": 4}, {"annot_id": "val-23096", "ind": 23096, "movie": "Reno 911!: Miami (2007)", "img_fn": "movieclips_Reno_911_Miami/9G4TzgRUKGI@17.jpg", "question_number": 5}, {"annot_id": "val-23097", "ind": 23097, "movie": "Half Baked (1998)", "img_fn": "movieclips_Half_Baked/H1JCgM_LHAg@37.jpg", "question_number": 2}, {"annot_id": "val-23098", "ind": 23098, "movie": "Bad Lieutenant (1992)", "img_fn": "movieclips_Bad_Lieutenant/BiO01_Fe6To@8.jpg", "question_number": 2}, {"annot_id": "val-23099", "ind": 23099, "movie": "Bad Lieutenant (1992)", "img_fn": "movieclips_Bad_Lieutenant/BiO01_Fe6To@8.jpg", "question_number": 3}, {"annot_id": "val-23100", "ind": 23100, "movie": "War of the Worlds (2005)", "img_fn": "movieclips_War_of_the_Worlds/rYGWG2_PB_Q@1.jpg", "question_number": 3}, {"annot_id": "val-23101", "ind": 23101, "movie": "War of the Worlds (2005)", "img_fn": "movieclips_War_of_the_Worlds/rYGWG2_PB_Q@1.jpg", "question_number": 4}, {"annot_id": "val-23102", "ind": 23102, "movie": "Midgets Vs. Mascots (2009)", "img_fn": "movieclips_Midgets_Vs._Mascots/51y64KtGGRI@51.jpg", "question_number": 2}, {"annot_id": "val-23103", "ind": 23103, "movie": "Employee of the Month (2006)", "img_fn": "movieclips_Employee_of_the_Month/gHf9n0jhBdk@0.jpg", "question_number": 2}, {"annot_id": "val-23104", "ind": 23104, "movie": "Employee of the Month (2006)", "img_fn": "movieclips_Employee_of_the_Month/gHf9n0jhBdk@0.jpg", "question_number": 3}, {"annot_id": "val-23105", "ind": 23105, "movie": "Employee of the Month (2006)", "img_fn": "movieclips_Employee_of_the_Month/gHf9n0jhBdk@0.jpg", "question_number": 4}, {"annot_id": "val-23106", "ind": 23106, "movie": "A Smile Like Yours (1997)", "img_fn": "movieclips_A_Smile_Like_Yours/8kiNT3_17i8@9.jpg", "question_number": 1}, {"annot_id": "val-23107", "ind": 23107, "movie": "Daddy's Home (2015)", "img_fn": "movieclips_Daddys_Home/vPYiq9JNq_c@25.jpg", "question_number": 2}, {"annot_id": "val-23108", "ind": 23108, "movie": "Basquiat (1996)", "img_fn": "movieclips_Basquiat/qM8jk56Vj9Y@12.jpg", "question_number": 1}, {"annot_id": "val-23109", "ind": 23109, "movie": "Basquiat (1996)", "img_fn": "movieclips_Basquiat/qM8jk56Vj9Y@12.jpg", "question_number": 2}, {"annot_id": "val-23110", "ind": 23110, "movie": "Basquiat (1996)", "img_fn": "movieclips_Basquiat/qM8jk56Vj9Y@12.jpg", "question_number": 3}, {"annot_id": "val-23111", "ind": 23111, "movie": "Happy Death Day (2017)", "img_fn": "movieclips_Happy_Death_Day/idvqLiOeLgc@57.jpg", "question_number": 3}, {"annot_id": "val-23112", "ind": 23112, "movie": "Happy Death Day (2017)", "img_fn": "movieclips_Happy_Death_Day/idvqLiOeLgc@57.jpg", "question_number": 4}, {"annot_id": "val-23113", "ind": 23113, "movie": "Cheaper by the Dozen (2003)", "img_fn": "movieclips_Cheaper_by_the_Dozen/1ZVwo_elP7Y@13.jpg", "question_number": 3}, {"annot_id": "val-23114", "ind": 23114, "movie": "Basquiat (1996)", "img_fn": "movieclips_Basquiat/LABD2un-vIs@7.jpg", "question_number": 1}, {"annot_id": "val-23115", "ind": 23115, "movie": "The Object of My Affection (1998)", "img_fn": "movieclips_The_Object_of_My_Affection/oKYBGq7pt3M@28.jpg", "question_number": 2}, {"annot_id": "val-23116", "ind": 23116, "movie": "What to Expect When You're Expecting (2012)", "img_fn": "movieclips_What_to_Expect_When_Youre_Expecting/yNkcLZ0BPuc@0.jpg", "question_number": 1}, {"annot_id": "val-23117", "ind": 23117, "movie": "What to Expect When You're Expecting (2012)", "img_fn": "movieclips_What_to_Expect_When_Youre_Expecting/yNkcLZ0BPuc@0.jpg", "question_number": 2}, {"annot_id": "val-23118", "ind": 23118, "movie": "The Nutty Professor (1996)", "img_fn": "movieclips_The_Nutty_Professor/i9NIwHKBqy0@46.jpg", "question_number": 1}, {"annot_id": "val-23119", "ind": 23119, "movie": "The Nutty Professor (1996)", "img_fn": "movieclips_The_Nutty_Professor/i9NIwHKBqy0@46.jpg", "question_number": 2}, {"annot_id": "val-23120", "ind": 23120, "movie": "The Nutty Professor (1996)", "img_fn": "movieclips_The_Nutty_Professor/i9NIwHKBqy0@46.jpg", "question_number": 3}, {"annot_id": "val-23121", "ind": 23121, "movie": "Epoch (2001)", "img_fn": "movieclips_Epoch/GNw7aQdAfcA@10.jpg", "question_number": 1}, {"annot_id": "val-23122", "ind": 23122, "movie": "Epoch (2001)", "img_fn": "movieclips_Epoch/GNw7aQdAfcA@10.jpg", "question_number": 2}, {"annot_id": "val-23123", "ind": 23123, "movie": "Epoch (2001)", "img_fn": "movieclips_Epoch/GNw7aQdAfcA@10.jpg", "question_number": 3}, {"annot_id": "val-23124", "ind": 23124, "movie": "Curse of the Pink Panther (1983)", "img_fn": "movieclips_Curse_of_the_Pink_Panther/P4PPhm_fJug@0.jpg", "question_number": 3}, {"annot_id": "val-23125", "ind": 23125, "movie": "A Mighty Wind (2003)", "img_fn": "movieclips_A_Mighty_Wind/sa2TE--j394@25.jpg", "question_number": 2}, {"annot_id": "val-23126", "ind": 23126, "movie": "A Mighty Wind (2003)", "img_fn": "movieclips_A_Mighty_Wind/sa2TE--j394@25.jpg", "question_number": 3}, {"annot_id": "val-23127", "ind": 23127, "movie": "A Mighty Wind (2003)", "img_fn": "movieclips_A_Mighty_Wind/sa2TE--j394@25.jpg", "question_number": 4}, {"annot_id": "val-23128", "ind": 23128, "movie": "American Pie 2 (2001)", "img_fn": "movieclips_American_Pie_2/hEDeIvU1si8@15.jpg", "question_number": 1}, {"annot_id": "val-23129", "ind": 23129, "movie": "American Pie 2 (2001)", "img_fn": "movieclips_American_Pie_2/hEDeIvU1si8@15.jpg", "question_number": 2}, {"annot_id": "val-23130", "ind": 23130, "movie": "American Pie 2 (2001)", "img_fn": "movieclips_American_Pie_2/hEDeIvU1si8@15.jpg", "question_number": 3}, {"annot_id": "val-23131", "ind": 23131, "movie": "Heat (1986)", "img_fn": "movieclips_Heat/KXa2pXA7v6I@19.jpg", "question_number": 1}, {"annot_id": "val-23132", "ind": 23132, "movie": "Heat (1986)", "img_fn": "movieclips_Heat/KXa2pXA7v6I@19.jpg", "question_number": 2}, {"annot_id": "val-23133", "ind": 23133, "movie": "The Way of the Gun (2000)", "img_fn": "movieclips_The_Way_of_the_Gun/ZIjuiq25Lzk@4.jpg", "question_number": 1}, {"annot_id": "val-23134", "ind": 23134, "movie": "The Way of the Gun (2000)", "img_fn": "movieclips_The_Way_of_the_Gun/ZIjuiq25Lzk@4.jpg", "question_number": 2}, {"annot_id": "val-23135", "ind": 23135, "movie": "The Way of the Gun (2000)", "img_fn": "movieclips_The_Way_of_the_Gun/ZIjuiq25Lzk@4.jpg", "question_number": 3}]